greengo/__init__.py
greengo/dns.py
greengo/dynamoEntry.py
greengo/elambdas.py
greengo/entity.py
greengo/greengo.py
greengo/group.py
greengo/lambdas.py
greengo/loggers.py
greengo/resources.py
greengo/shadow.py
greengo/state.py
greengo/subscriptions.py
greengo/utils.py
gud-2.0.18.dist-info/LICENSE.txt
gud-2.0.18.dist-info/METADATA
gud-2.0.18.dist-info/WHEEL
gud-2.0.18.dist-info/entry_points.txt
gud-2.0.18.dist-info/top_level.txt
gud-2.0.18.dist-info/RECORD
