Metadata-Version: 2.1
Name: gud
Version: 2.0.18
Summary: AWS Greengrass file-based setup tool based on greengo by d
Home-page: https://gitlab.com/doopnz/gud
Author: Dmitri Zimine modified by James Whiteman
Author-email: james.whiteman@gmail.com
License: MIT
Keywords: AWS,IoT,Greengrass,Lambda
Platform: UNKNOWN
Requires-Dist: boto3
Requires-Dist: botocore
Requires-Dist: fire
Requires-Dist: pyyaml
